eurovoc/__init__.py
eurovoc/en_identifiers.py
eurovoc/en_labels.py
eurovoc/thesaurus_en_labels.py
eurovoc/thesaurus_uris.py
eurovoc/version.py
eurovoc-23.10.16.0.dist-info/METADATA
eurovoc-23.10.16.0.dist-info/WHEEL
eurovoc-23.10.16.0.dist-info/top_level.txt
eurovoc-23.10.16.0.dist-info/RECORD
