Metadata-Version: 2.1
Name: eurovoc
Version: 23.10.16.0
Summary: Extract EuroVoc from the EU website
Home-page: https://github.com/scampion/eurovoc
Author: Sebastien Campion
License: MIT
Requires-Dist: joblib ==1.2.0
